Compiled from "Item.java"
public class net.minecraft.world.item.Item$Properties {
  public net.minecraft.world.item.Item$Properties();
    Code:
         0: aload_0
         1: invokespecial #1                  // Method java/lang/Object."<init>":()V
         4: aload_0
         5: invokedynamic #7,  0              // InvokeDynamic #0:run:()Lnet/minecraft/core/component/DataComponentInitializers$Initializer;
        10: putfield      #11                 // Field componentInitializer:Lnet/minecraft/core/component/DataComponentInitializers$Initializer;
        13: aload_0
        14: getstatic     #17                 // Field net/minecraft/world/flag/FeatureFlags.VANILLA_SET:Lnet/minecraft/world/flag/FeatureFlagSet;
        17: putfield      #23                 // Field requiredFeatures:Lnet/minecraft/world/flag/FeatureFlagSet;
        20: aload_0
        21: getstatic     #26                 // Field ITEM_DESCRIPTION_ID:Lnet/minecraft/resources/DependantName;
        24: putfield      #30                 // Field descriptionId:Lnet/minecraft/resources/DependantName;
        27: aload_0
        28: invokedynamic #33,  0             // InvokeDynamic #1:get:()Lnet/minecraft/resources/DependantName;
        33: putfield      #37                 // Field model:Lnet/minecraft/resources/DependantName;
        36: return

  public net.minecraft.world.item.Item$Properties food(net.minecraft.world.food.FoodProperties);
    Code:
         0: aload_0
         1: aload_1
         2: getstatic     #40                 // Field net/minecraft/world/item/component/Consumables.DEFAULT_FOOD:Lnet/minecraft/world/item/component/Consumable;
         5: invokevirtual #46                 // Method food:(Lnet/minecraft/world/food/FoodProperties;Lnet/minecraft/world/item/component/Consumable;)Lnet/minecraft/world/item/Item$Properties;
         8: areturn

  public net.minecraft.world.item.Item$Properties food(net.minecraft.world.food.FoodProperties, net.minecraft.world.item.component.Consumable);
    Code:
         0: aload_0
         1: getstatic     #50                 // Field net/minecraft/core/component/DataComponents.FOOD:Lnet/minecraft/core/component/DataComponentType;
         4: aload_1
         5: invokevirtual #56                 // Method component:(Lnet/minecraft/core/component/DataComponentType;Ljava/lang/Object;)Lnet/minecraft/world/item/Item$Properties;
         8: getstatic     #60                 // Field net/minecraft/core/component/DataComponents.CONSUMABLE:Lnet/minecraft/core/component/DataComponentType;
        11: aload_2
        12: invokevirtual #56                 // Method component:(Lnet/minecraft/core/component/DataComponentType;Ljava/lang/Object;)Lnet/minecraft/world/item/Item$Properties;
        15: areturn

  public net.minecraft.world.item.Item$Properties usingConvertsTo(net.minecraft.world.item.Item);
    Code:
         0: aload_0
         1: getstatic     #63                 // Field net/minecraft/core/component/DataComponents.USE_REMAINDER:Lnet/minecraft/core/component/DataComponentType;
         4: new           #66                 // class net/minecraft/world/item/component/UseRemainder
         7: dup
         8: new           #68                 // class net/minecraft/world/item/ItemStackTemplate
        11: dup
        12: aload_1
        13: invokespecial #70                 // Method net/minecraft/world/item/ItemStackTemplate."<init>":(Lnet/minecraft/world/item/Item;)V
        16: invokespecial #73                 // Method net/minecraft/world/item/component/UseRemainder."<init>":(Lnet/minecraft/world/item/ItemStackTemplate;)V
        19: invokevirtual #56                 // Method component:(Lnet/minecraft/core/component/DataComponentType;Ljava/lang/Object;)Lnet/minecraft/world/item/Item$Properties;
        22: areturn

  public net.minecraft.world.item.Item$Properties useCooldown(float);
    Code:
         0: aload_0
         1: getstatic     #76                 // Field net/minecraft/core/component/DataComponents.USE_COOLDOWN:Lnet/minecraft/core/component/DataComponentType;
         4: new           #79                 // class net/minecraft/world/item/component/UseCooldown
         7: dup
         8: fload_1
         9: invokespecial #81                 // Method net/minecraft/world/item/component/UseCooldown."<init>":(F)V
        12: invokevirtual #56                 // Method component:(Lnet/minecraft/core/component/DataComponentType;Ljava/lang/Object;)Lnet/minecraft/world/item/Item$Properties;
        15: areturn

  public net.minecraft.world.item.Item$Properties stacksTo(int);
    Code:
         0: aload_0
         1: getstatic     #84                 // Field net/minecraft/core/component/DataComponents.MAX_STACK_SIZE:Lnet/minecraft/core/component/DataComponentType;
         4: iload_1
         5: invokestatic  #87                 // Method java/lang/Integer.valueOf:(I)Ljava/lang/Integer;
         8: invokevirtual #56                 // Method component:(Lnet/minecraft/core/component/DataComponentType;Ljava/lang/Object;)Lnet/minecraft/world/item/Item$Properties;
        11: areturn

  public net.minecraft.world.item.Item$Properties durability(int);
    Code:
         0: aload_0
         1: getstatic     #93                 // Field net/minecraft/core/component/DataComponents.MAX_DAMAGE:Lnet/minecraft/core/component/DataComponentType;
         4: iload_1
         5: invokestatic  #87                 // Method java/lang/Integer.valueOf:(I)Ljava/lang/Integer;
         8: invokevirtual #56                 // Method component:(Lnet/minecraft/core/component/DataComponentType;Ljava/lang/Object;)Lnet/minecraft/world/item/Item$Properties;
        11: pop
        12: aload_0
        13: getstatic     #84                 // Field net/minecraft/core/component/DataComponents.MAX_STACK_SIZE:Lnet/minecraft/core/component/DataComponentType;
        16: iconst_1
        17: invokestatic  #87                 // Method java/lang/Integer.valueOf:(I)Ljava/lang/Integer;
        20: invokevirtual #56                 // Method component:(Lnet/minecraft/core/component/DataComponentType;Ljava/lang/Object;)Lnet/minecraft/world/item/Item$Properties;
        23: pop
        24: aload_0
        25: getstatic     #96                 // Field net/minecraft/core/component/DataComponents.DAMAGE:Lnet/minecraft/core/component/DataComponentType;
        28: iconst_0
        29: invokestatic  #87                 // Method java/lang/Integer.valueOf:(I)Ljava/lang/Integer;
        32: invokevirtual #56                 // Method component:(Lnet/minecraft/core/component/DataComponentType;Ljava/lang/Object;)Lnet/minecraft/world/item/Item$Properties;
        35: pop
        36: aload_0
        37: areturn

  public net.minecraft.world.item.Item$Properties craftRemainder(net.minecraft.world.item.Item);
    Code:
         0: aload_0
         1: new           #68                 // class net/minecraft/world/item/ItemStackTemplate
         4: dup
         5: aload_1
         6: invokespecial #70                 // Method net/minecraft/world/item/ItemStackTemplate."<init>":(Lnet/minecraft/world/item/Item;)V
         9: invokevirtual #99                 // Method craftRemainder:(Lnet/minecraft/world/item/ItemStackTemplate;)Lnet/minecraft/world/item/Item$Properties;
        12: areturn

  public net.minecraft.world.item.Item$Properties craftRemainder(net.minecraft.world.item.ItemStackTemplate);
    Code:
         0: aload_0
         1: aload_1
         2: putfield      #103                // Field craftingRemainingItem:Lnet/minecraft/world/item/ItemStackTemplate;
         5: aload_0
         6: areturn

  public net.minecraft.world.item.Item$Properties rarity(net.minecraft.world.item.Rarity);
    Code:
         0: aload_0
         1: getstatic     #107                // Field net/minecraft/core/component/DataComponents.RARITY:Lnet/minecraft/core/component/DataComponentType;
         4: aload_1
         5: invokevirtual #56                 // Method component:(Lnet/minecraft/core/component/DataComponentType;Ljava/lang/Object;)Lnet/minecraft/world/item/Item$Properties;
         8: areturn

  public net.minecraft.world.item.Item$Properties fireResistant();
    Code:
         0: aload_0
         1: getstatic     #110                // Field net/minecraft/core/component/DataComponents.DAMAGE_RESISTANT:Lnet/minecraft/core/component/DataComponentType;
         4: invokedynamic #113,  0            // InvokeDynamic #2:create:()Lnet/minecraft/core/component/DataComponentInitializers$SingleComponentInitializer;
         9: invokevirtual #117                // Method delayedComponent:(Lnet/minecraft/core/component/DataComponentType;Lnet/minecraft/core/component/DataComponentInitializers$SingleComponentInitializer;)Lnet/minecraft/world/item/Item$Properties;
        12: areturn

  public net.minecraft.world.item.Item$Properties jukeboxPlayable(net.minecraft.resources.ResourceKey<net.minecraft.world.item.JukeboxSong>);
    Code:
         0: aload_0
         1: getstatic     #121                // Field net/minecraft/core/component/DataComponents.JUKEBOX_PLAYABLE:Lnet/minecraft/core/component/DataComponentType;
         4: aload_1
         5: invokedynamic #124,  0            // InvokeDynamic #3:create:(Lnet/minecraft/resources/ResourceKey;)Lnet/minecraft/core/component/DataComponentInitializers$SingleComponentInitializer;
        10: invokevirtual #117                // Method delayedComponent:(Lnet/minecraft/core/component/DataComponentType;Lnet/minecraft/core/component/DataComponentInitializers$SingleComponentInitializer;)Lnet/minecraft/world/item/Item$Properties;
        13: areturn

  public net.minecraft.world.item.Item$Properties enchantable(int);
    Code:
         0: aload_0
         1: getstatic     #127                // Field net/minecraft/core/component/DataComponents.ENCHANTABLE:Lnet/minecraft/core/component/DataComponentType;
         4: new           #130                // class net/minecraft/world/item/enchantment/Enchantable
         7: dup
         8: iload_1
         9: invokespecial #132                // Method net/minecraft/world/item/enchantment/Enchantable."<init>":(I)V
        12: invokevirtual #56                 // Method component:(Lnet/minecraft/core/component/DataComponentType;Ljava/lang/Object;)Lnet/minecraft/world/item/Item$Properties;
        15: areturn

  public net.minecraft.world.item.Item$Properties repairable(net.minecraft.world.item.Item);
    Code:
         0: aload_0
         1: getstatic     #135                // Field net/minecraft/core/component/DataComponents.REPAIRABLE:Lnet/minecraft/core/component/DataComponentType;
         4: new           #138                // class net/minecraft/world/item/enchantment/Repairable
         7: dup
         8: iconst_1
         9: anewarray     #140                // class net/minecraft/core/Holder
        12: dup
        13: iconst_0
        14: aload_1
        15: invokevirtual #142                // Method net/minecraft/world/item/Item.builtInRegistryHolder:()Lnet/minecraft/core/Holder$Reference;
        18: aastore
        19: invokestatic  #148                // InterfaceMethod net/minecraft/core/HolderSet.direct:([Lnet/minecraft/core/Holder;)Lnet/minecraft/core/HolderSet$Direct;
        22: invokespecial #154                // Method net/minecraft/world/item/enchantment/Repairable."<init>":(Lnet/minecraft/core/HolderSet;)V
        25: invokevirtual #56                 // Method component:(Lnet/minecraft/core/component/DataComponentType;Ljava/lang/Object;)Lnet/minecraft/world/item/Item$Properties;
        28: areturn

  public net.minecraft.world.item.Item$Properties repairable(net.minecraft.tags.TagKey<net.minecraft.world.item.Item>);
    Code:
         0: getstatic     #157                // Field net/minecraft/core/registries/BuiltInRegistries.ITEM:Lnet/minecraft/core/DefaultedRegistry;
         3: invokestatic  #163                // Method net/minecraft/core/registries/BuiltInRegistries.acquireBootstrapRegistrationLookup:(Lnet/minecraft/core/Registry;)Lnet/minecraft/core/HolderGetter;
         6: astore_2
         7: aload_0
         8: getstatic     #135                // Field net/minecraft/core/component/DataComponents.REPAIRABLE:Lnet/minecraft/core/component/DataComponentType;
        11: new           #138                // class net/minecraft/world/item/enchantment/Repairable
        14: dup
        15: aload_2
        16: aload_1
        17: invokeinterface #167,  2          // InterfaceMethod net/minecraft/core/HolderGetter.getOrThrow:(Lnet/minecraft/tags/TagKey;)Lnet/minecraft/core/HolderSet$Named;
        22: invokespecial #154                // Method net/minecraft/world/item/enchantment/Repairable."<init>":(Lnet/minecraft/core/HolderSet;)V
        25: invokevirtual #56                 // Method component:(Lnet/minecraft/core/component/DataComponentType;Ljava/lang/Object;)Lnet/minecraft/world/item/Item$Properties;
        28: areturn

  public net.minecraft.world.item.Item$Properties equippable(net.minecraft.world.entity.EquipmentSlot);
    Code:
         0: aload_0
         1: getstatic     #173                // Field net/minecraft/core/component/DataComponents.EQUIPPABLE:Lnet/minecraft/core/component/DataComponentType;
         4: aload_1
         5: invokestatic  #176                // Method net/minecraft/world/item/equipment/Equippable.builder:(Lnet/minecraft/world/entity/EquipmentSlot;)Lnet/minecraft/world/item/equipment/Equippable$Builder;
         8: invokevirtual #182                // Method net/minecraft/world/item/equipment/Equippable$Builder.build:()Lnet/minecraft/world/item/equipment/Equippable;
        11: invokevirtual #56                 // Method component:(Lnet/minecraft/core/component/DataComponentType;Ljava/lang/Object;)Lnet/minecraft/world/item/Item$Properties;
        14: areturn

  public net.minecraft.world.item.Item$Properties equippableUnswappable(net.minecraft.world.entity.EquipmentSlot);
    Code:
         0: aload_0
         1: getstatic     #173                // Field net/minecraft/core/component/DataComponents.EQUIPPABLE:Lnet/minecraft/core/component/DataComponentType;
         4: aload_1
         5: invokestatic  #176                // Method net/minecraft/world/item/equipment/Equippable.builder:(Lnet/minecraft/world/entity/EquipmentSlot;)Lnet/minecraft/world/item/equipment/Equippable$Builder;
         8: iconst_0
         9: invokevirtual #188                // Method net/minecraft/world/item/equipment/Equippable$Builder.setSwappable:(Z)Lnet/minecraft/world/item/equipment/Equippable$Builder;
        12: invokevirtual #182                // Method net/minecraft/world/item/equipment/Equippable$Builder.build:()Lnet/minecraft/world/item/equipment/Equippable;
        15: invokevirtual #56                 // Method component:(Lnet/minecraft/core/component/DataComponentType;Ljava/lang/Object;)Lnet/minecraft/world/item/Item$Properties;
        18: areturn

  public net.minecraft.world.item.Item$Properties tool(net.minecraft.world.item.ToolMaterial, net.minecraft.tags.TagKey<net.minecraft.world.level.block.Block>, float, float, float);
    Code:
         0: aload_1
         1: aload_0
         2: aload_2
         3: fload_3
         4: fload         4
         6: fload         5
         8: invokevirtual #192                // Method net/minecraft/world/item/ToolMaterial.applyToolProperties:(Lnet/minecraft/world/item/Item$Properties;Lnet/minecraft/tags/TagKey;FFF)Lnet/minecraft/world/item/Item$Properties;
        11: areturn

  public net.minecraft.world.item.Item$Properties pickaxe(net.minecraft.world.item.ToolMaterial, float, float);
    Code:
         0: aload_0
         1: aload_1
         2: getstatic     #198                // Field net/minecraft/tags/BlockTags.MINEABLE_WITH_PICKAXE:Lnet/minecraft/tags/TagKey;
         5: fload_2
         6: fload_3
         7: fconst_0
         8: invokevirtual #204                // Method tool:(Lnet/minecraft/world/item/ToolMaterial;Lnet/minecraft/tags/TagKey;FFF)Lnet/minecraft/world/item/Item$Properties;
        11: areturn

  public net.minecraft.world.item.Item$Properties axe(net.minecraft.world.item.ToolMaterial, float, float);
    Code:
         0: aload_0
         1: aload_1
         2: getstatic     #208                // Field net/minecraft/tags/BlockTags.MINEABLE_WITH_AXE:Lnet/minecraft/tags/TagKey;
         5: fload_2
         6: fload_3
         7: ldc           #213                // float 5.0f
         9: invokevirtual #204                // Method tool:(Lnet/minecraft/world/item/ToolMaterial;Lnet/minecraft/tags/TagKey;FFF)Lnet/minecraft/world/item/Item$Properties;
        12: areturn

  public net.minecraft.world.item.Item$Properties hoe(net.minecraft.world.item.ToolMaterial, float, float);
    Code:
         0: aload_0
         1: aload_1
         2: getstatic     #214                // Field net/minecraft/tags/BlockTags.MINEABLE_WITH_HOE:Lnet/minecraft/tags/TagKey;
         5: fload_2
         6: fload_3
         7: fconst_0
         8: invokevirtual #204                // Method tool:(Lnet/minecraft/world/item/ToolMaterial;Lnet/minecraft/tags/TagKey;FFF)Lnet/minecraft/world/item/Item$Properties;
        11: areturn

  public net.minecraft.world.item.Item$Properties shovel(net.minecraft.world.item.ToolMaterial, float, float);
    Code:
         0: aload_0
         1: aload_1
         2: getstatic     #217                // Field net/minecraft/tags/BlockTags.MINEABLE_WITH_SHOVEL:Lnet/minecraft/tags/TagKey;
         5: fload_2
         6: fload_3
         7: fconst_0
         8: invokevirtual #204                // Method tool:(Lnet/minecraft/world/item/ToolMaterial;Lnet/minecraft/tags/TagKey;FFF)Lnet/minecraft/world/item/Item$Properties;
        11: areturn

  public net.minecraft.world.item.Item$Properties sword(net.minecraft.world.item.ToolMaterial, float, float);
    Code:
         0: aload_1
         1: aload_0
         2: fload_2
         3: fload_3
         4: invokevirtual #220                // Method net/minecraft/world/item/ToolMaterial.applySwordProperties:(Lnet/minecraft/world/item/Item$Properties;FF)Lnet/minecraft/world/item/Item$Properties;
         7: areturn

  public net.minecraft.world.item.Item$Properties spear(net.minecraft.world.item.ToolMaterial, float, float, float, float, float, float, float, float, float);
    Code:
         0: aload_0
         1: aload_1
         2: invokevirtual #224                // Method net/minecraft/world/item/ToolMaterial.durability:()I
         5: invokevirtual #228                // Method durability:(I)Lnet/minecraft/world/item/Item$Properties;
         8: aload_1
         9: invokevirtual #231                // Method net/minecraft/world/item/ToolMaterial.repairItems:()Lnet/minecraft/tags/TagKey;
        12: invokevirtual #235                // Method repairable:(Lnet/minecraft/tags/TagKey;)Lnet/minecraft/world/item/Item$Properties;
        15: aload_1
        16: invokevirtual #239                // Method net/minecraft/world/item/ToolMaterial.enchantmentValue:()I
        19: invokevirtual #242                // Method enchantable:(I)Lnet/minecraft/world/item/Item$Properties;
        22: getstatic     #245                // Field net/minecraft/core/component/DataComponents.DAMAGE_TYPE:Lnet/minecraft/core/component/DataComponentType;
        25: getstatic     #248                // Field net/minecraft/world/damagesource/DamageTypes.SPEAR:Lnet/minecraft/resources/ResourceKey;
        28: invokevirtual #254                // Method delayedHolderComponent:(Lnet/minecraft/core/component/DataComponentType;Lnet/minecraft/resources/ResourceKey;)Lnet/minecraft/world/item/Item$Properties;
        31: getstatic     #258                // Field net/minecraft/core/component/DataComponents.KINETIC_WEAPON:Lnet/minecraft/core/component/DataComponentType;
        34: new           #261                // class net/minecraft/world/item/component/KineticWeapon
        37: dup
        38: bipush        10
        40: fload         4
        42: ldc_w         #265                // float 20.0f
        45: fmul
        46: f2i
        47: fload         5
        49: ldc_w         #265                // float 20.0f
        52: fmul
        53: f2i
        54: fload         6
        56: invokestatic  #266                // Method net/minecraft/world/item/component/KineticWeapon$Condition.ofAttackerSpeed:(IF)Ljava/util/Optional;
        59: fload         7
        61: ldc_w         #265                // float 20.0f
        64: fmul
        65: f2i
        66: fload         8
        68: invokestatic  #266                // Method net/minecraft/world/item/component/KineticWeapon$Condition.ofAttackerSpeed:(IF)Ljava/util/Optional;
        71: fload         9
        73: ldc_w         #265                // float 20.0f
        76: fmul
        77: f2i
        78: fload         10
        80: invokestatic  #272                // Method net/minecraft/world/item/component/KineticWeapon$Condition.ofRelativeSpeed:(IF)Ljava/util/Optional;
        83: ldc_w         #275                // float 0.38f
        86: fload_3
        87: aload_1
        88: getstatic     #276                // Field net/minecraft/world/item/ToolMaterial.WOOD:Lnet/minecraft/world/item/ToolMaterial;
        91: if_acmpne     100
        94: getstatic     #280                // Field net/minecraft/sounds/SoundEvents.SPEAR_WOOD_USE:Lnet/minecraft/core/Holder;
        97: goto          103
       100: getstatic     #286                // Field net/minecraft/sounds/SoundEvents.SPEAR_USE:Lnet/minecraft/core/Holder;
       103: invokestatic  #289                // Method java/util/Optional.of:(Ljava/lang/Object;)Ljava/util/Optional;
       106: aload_1
       107: getstatic     #276                // Field net/minecraft/world/item/ToolMaterial.WOOD:Lnet/minecraft/world/item/ToolMaterial;
       110: if_acmpne     119
       113: getstatic     #295                // Field net/minecraft/sounds/SoundEvents.SPEAR_WOOD_HIT:Lnet/minecraft/core/Holder;
       116: goto          122
       119: getstatic     #298                // Field net/minecraft/sounds/SoundEvents.SPEAR_HIT:Lnet/minecraft/core/Holder;
       122: invokestatic  #289                // Method java/util/Optional.of:(Ljava/lang/Object;)Ljava/util/Optional;
       125: invokespecial #301                // Method net/minecraft/world/item/component/KineticWeapon."<init>":(IILjava/util/Optional;Ljava/util/Optional;Ljava/util/Optional;FFLjava/util/Optional;Ljava/util/Optional;)V
       128: invokevirtual #56                 // Method component:(Lnet/minecraft/core/component/DataComponentType;Ljava/lang/Object;)Lnet/minecraft/world/item/Item$Properties;
       131: getstatic     #304                // Field net/minecraft/core/component/DataComponents.PIERCING_WEAPON:Lnet/minecraft/core/component/DataComponentType;
       134: new           #307                // class net/minecraft/world/item/component/PiercingWeapon
       137: dup
       138: iconst_1
       139: iconst_0
       140: aload_1
       141: getstatic     #276                // Field net/minecraft/world/item/ToolMaterial.WOOD:Lnet/minecraft/world/item/ToolMaterial;
       144: if_acmpne     153
       147: getstatic     #309                // Field net/minecraft/sounds/SoundEvents.SPEAR_WOOD_ATTACK:Lnet/minecraft/core/Holder;
       150: goto          156
       153: getstatic     #312                // Field net/minecraft/sounds/SoundEvents.SPEAR_ATTACK:Lnet/minecraft/core/Holder;
       156: invokestatic  #289                // Method java/util/Optional.of:(Ljava/lang/Object;)Ljava/util/Optional;
       159: aload_1
       160: getstatic     #276                // Field net/minecraft/world/item/ToolMaterial.WOOD:Lnet/minecraft/world/item/ToolMaterial;
       163: if_acmpne     172
       166: getstatic     #295                // Field net/minecraft/sounds/SoundEvents.SPEAR_WOOD_HIT:Lnet/minecraft/core/Holder;
       169: goto          175
       172: getstatic     #298                // Field net/minecraft/sounds/SoundEvents.SPEAR_HIT:Lnet/minecraft/core/Holder;
       175: invokestatic  #289                // Method java/util/Optional.of:(Ljava/lang/Object;)Ljava/util/Optional;
       178: invokespecial #315                // Method net/minecraft/world/item/component/PiercingWeapon."<init>":(ZZLjava/util/Optional;Ljava/util/Optional;)V
       181: invokevirtual #56                 // Method component:(Lnet/minecraft/core/component/DataComponentType;Ljava/lang/Object;)Lnet/minecraft/world/item/Item$Properties;
       184: getstatic     #318                // Field net/minecraft/core/component/DataComponents.ATTACK_RANGE:Lnet/minecraft/core/component/DataComponentType;
       187: new           #321                // class net/minecraft/world/item/component/AttackRange
       190: dup
       191: fconst_2
       192: ldc_w         #323                // float 4.5f
       195: fconst_2
       196: ldc_w         #326                // float 6.5f
       199: ldc_w         #327                // float 0.125f
       202: ldc_w         #328                // float 0.5f
       205: invokespecial #329                // Method net/minecraft/world/item/component/AttackRange."<init>":(FFFFFF)V
       208: invokevirtual #56                 // Method component:(Lnet/minecraft/core/component/DataComponentType;Ljava/lang/Object;)Lnet/minecraft/world/item/Item$Properties;
       211: getstatic     #332                // Field net/minecraft/core/component/DataComponents.MINIMUM_ATTACK_CHARGE:Lnet/minecraft/core/component/DataComponentType;
       214: fconst_1
       215: invokestatic  #335                // Method java/lang/Float.valueOf:(F)Ljava/lang/Float;
       218: invokevirtual #56                 // Method component:(Lnet/minecraft/core/component/DataComponentType;Ljava/lang/Object;)Lnet/minecraft/world/item/Item$Properties;
       221: getstatic     #340                // Field net/minecraft/core/component/DataComponents.SWING_ANIMATION:Lnet/minecraft/core/component/DataComponentType;
       224: new           #343                // class net/minecraft/world/item/component/SwingAnimation
       227: dup
       228: getstatic     #345                // Field net/minecraft/world/item/SwingAnimationType.STAB:Lnet/minecraft/world/item/SwingAnimationType;
       231: fload_2
       232: ldc_w         #265                // float 20.0f
       235: fmul
       236: f2i
       237: invokespecial #351                // Method net/minecraft/world/item/component/SwingAnimation."<init>":(Lnet/minecraft/world/item/SwingAnimationType;I)V
       240: invokevirtual #56                 // Method component:(Lnet/minecraft/core/component/DataComponentType;Ljava/lang/Object;)Lnet/minecraft/world/item/Item$Properties;
       243: invokestatic  #354                // Method net/minecraft/world/item/component/ItemAttributeModifiers.builder:()Lnet/minecraft/world/item/component/ItemAttributeModifiers$Builder;
       246: getstatic     #359                // Field net/minecraft/world/entity/ai/attributes/Attributes.ATTACK_DAMAGE:Lnet/minecraft/core/Holder;
       249: new           #364                // class net/minecraft/world/entity/ai/attributes/AttributeModifier
       252: dup
       253: getstatic     #366                // Field net/minecraft/world/item/Item.BASE_ATTACK_DAMAGE_ID:Lnet/minecraft/resources/Identifier;
       256: fconst_0
       257: aload_1
       258: invokevirtual #370                // Method net/minecraft/world/item/ToolMaterial.attackDamageBonus:()F
       261: fadd
       262: f2d
       263: getstatic     #374                // Field net/minecraft/world/entity/ai/attributes/AttributeModifier$Operation.ADD_VALUE:Lnet/minecraft/world/entity/ai/attributes/AttributeModifier$Operation;
       266: invokespecial #380                // Method net/minecraft/world/entity/ai/attributes/AttributeModifier."<init>":(Lnet/minecraft/resources/Identifier;DLnet/minecraft/world/entity/ai/attributes/AttributeModifier$Operation;)V
       269: getstatic     #383                // Field net/minecraft/world/entity/EquipmentSlotGroup.MAINHAND:Lnet/minecraft/world/entity/EquipmentSlotGroup;
       272: invokevirtual #389                // Method net/minecraft/world/item/component/ItemAttributeModifiers$Builder.add:(Lnet/minecraft/core/Holder;Lnet/minecraft/world/entity/ai/attributes/AttributeModifier;Lnet/minecraft/world/entity/EquipmentSlotGroup;)Lnet/minecraft/world/item/component/ItemAttributeModifiers$Builder;
       275: getstatic     #395                // Field net/minecraft/world/entity/ai/attributes/Attributes.ATTACK_SPEED:Lnet/minecraft/core/Holder;
       278: new           #364                // class net/minecraft/world/entity/ai/attributes/AttributeModifier
       281: dup
       282: getstatic     #398                // Field net/minecraft/world/item/Item.BASE_ATTACK_SPEED_ID:Lnet/minecraft/resources/Identifier;
       285: fconst_1
       286: fload_2
       287: fdiv
       288: f2d
       289: ldc2_w        #401                // double 4.0d
       292: dsub
       293: getstatic     #374                // Field net/minecraft/world/entity/ai/attributes/AttributeModifier$Operation.ADD_VALUE:Lnet/minecraft/world/entity/ai/attributes/AttributeModifier$Operation;
       296: invokespecial #380                // Method net/minecraft/world/entity/ai/attributes/AttributeModifier."<init>":(Lnet/minecraft/resources/Identifier;DLnet/minecraft/world/entity/ai/attributes/AttributeModifier$Operation;)V
       299: getstatic     #383                // Field net/minecraft/world/entity/EquipmentSlotGroup.MAINHAND:Lnet/minecraft/world/entity/EquipmentSlotGroup;
       302: invokevirtual #389                // Method net/minecraft/world/item/component/ItemAttributeModifiers$Builder.add:(Lnet/minecraft/core/Holder;Lnet/minecraft/world/entity/ai/attributes/AttributeModifier;Lnet/minecraft/world/entity/EquipmentSlotGroup;)Lnet/minecraft/world/item/component/ItemAttributeModifiers$Builder;
       305: invokevirtual #403                // Method net/minecraft/world/item/component/ItemAttributeModifiers$Builder.build:()Lnet/minecraft/world/item/component/ItemAttributeModifiers;
       308: invokevirtual #406                // Method attributes:(Lnet/minecraft/world/item/component/ItemAttributeModifiers;)Lnet/minecraft/world/item/Item$Properties;
       311: getstatic     #410                // Field net/minecraft/core/component/DataComponents.USE_EFFECTS:Lnet/minecraft/core/component/DataComponentType;
       314: new           #413                // class net/minecraft/world/item/component/UseEffects
       317: dup
       318: iconst_1
       319: iconst_0
       320: fconst_1
       321: invokespecial #415                // Method net/minecraft/world/item/component/UseEffects."<init>":(ZZF)V
       324: invokevirtual #56                 // Method component:(Lnet/minecraft/core/component/DataComponentType;Ljava/lang/Object;)Lnet/minecraft/world/item/Item$Properties;
       327: getstatic     #418                // Field net/minecraft/core/component/DataComponents.WEAPON:Lnet/minecraft/core/component/DataComponentType;
       330: new           #211                // class net/minecraft/world/item/component/Weapon
       333: dup
       334: iconst_1
       335: invokespecial #421                // Method net/minecraft/world/item/component/Weapon."<init>":(I)V
       338: invokevirtual #56                 // Method component:(Lnet/minecraft/core/component/DataComponentType;Ljava/lang/Object;)Lnet/minecraft/world/item/Item$Properties;
       341: areturn

  public net.minecraft.world.item.Item$Properties spawnEgg(net.minecraft.world.entity.EntityType<?>);
    Code:
         0: aload_0
         1: getstatic     #422                // Field net/minecraft/core/component/DataComponents.ENTITY_DATA:Lnet/minecraft/core/component/DataComponentType;
         4: aload_1
         5: new           #425                // class net/minecraft/nbt/CompoundTag
         8: dup
         9: invokespecial #427                // Method net/minecraft/nbt/CompoundTag."<init>":()V
        12: invokestatic  #428                // Method net/minecraft/world/item/component/TypedEntityData.of:(Ljava/lang/Object;Lnet/minecraft/nbt/CompoundTag;)Lnet/minecraft/world/item/component/TypedEntityData;
        15: invokevirtual #56                 // Method component:(Lnet/minecraft/core/component/DataComponentType;Ljava/lang/Object;)Lnet/minecraft/world/item/Item$Properties;
        18: aload_1
        19: invokevirtual #433                // Method net/minecraft/world/entity/EntityType.requiredFeatures:()Lnet/minecraft/world/flag/FeatureFlagSet;
        22: invokevirtual #438                // Method requiredFeatures:(Lnet/minecraft/world/flag/FeatureFlagSet;)Lnet/minecraft/world/item/Item$Properties;
        25: areturn

  public net.minecraft.world.item.Item$Properties humanoidArmor(net.minecraft.world.item.equipment.ArmorMaterial, net.minecraft.world.item.equipment.ArmorType);
    Code:
         0: aload_0
         1: aload_2
         2: aload_1
         3: invokevirtual #441                // Method net/minecraft/world/item/equipment/ArmorMaterial.durability:()I
         6: invokevirtual #444                // Method net/minecraft/world/item/equipment/ArmorType.getDurability:(I)I
         9: invokevirtual #228                // Method durability:(I)Lnet/minecraft/world/item/Item$Properties;
        12: aload_1
        13: aload_2
        14: invokevirtual #450                // Method net/minecraft/world/item/equipment/ArmorMaterial.createAttributes:(Lnet/minecraft/world/item/equipment/ArmorType;)Lnet/minecraft/world/item/component/ItemAttributeModifiers;
        17: invokevirtual #406                // Method attributes:(Lnet/minecraft/world/item/component/ItemAttributeModifiers;)Lnet/minecraft/world/item/Item$Properties;
        20: aload_1
        21: invokevirtual #454                // Method net/minecraft/world/item/equipment/ArmorMaterial.enchantmentValue:()I
        24: invokevirtual #242                // Method enchantable:(I)Lnet/minecraft/world/item/Item$Properties;
        27: getstatic     #173                // Field net/minecraft/core/component/DataComponents.EQUIPPABLE:Lnet/minecraft/core/component/DataComponentType;
        30: aload_2
        31: invokevirtual #455                // Method net/minecraft/world/item/equipment/ArmorType.getSlot:()Lnet/minecraft/world/entity/EquipmentSlot;
        34: invokestatic  #176                // Method net/minecraft/world/item/equipment/Equippable.builder:(Lnet/minecraft/world/entity/EquipmentSlot;)Lnet/minecraft/world/item/equipment/Equippable$Builder;
        37: aload_1
        38: invokevirtual #459                // Method net/minecraft/world/item/equipment/ArmorMaterial.equipSound:()Lnet/minecraft/core/Holder;
        41: invokevirtual #463                // Method net/minecraft/world/item/equipment/Equippable$Builder.setEquipSound:(Lnet/minecraft/core/Holder;)Lnet/minecraft/world/item/equipment/Equippable$Builder;
        44: aload_1
        45: invokevirtual #467                // Method net/minecraft/world/item/equipment/ArmorMaterial.assetId:()Lnet/minecraft/resources/ResourceKey;
        48: invokevirtual #471                // Method net/minecraft/world/item/equipment/Equippable$Builder.setAsset:(Lnet/minecraft/resources/ResourceKey;)Lnet/minecraft/world/item/equipment/Equippable$Builder;
        51: invokevirtual #182                // Method net/minecraft/world/item/equipment/Equippable$Builder.build:()Lnet/minecraft/world/item/equipment/Equippable;
        54: invokevirtual #56                 // Method component:(Lnet/minecraft/core/component/DataComponentType;Ljava/lang/Object;)Lnet/minecraft/world/item/Item$Properties;
        57: aload_1
        58: invokevirtual #475                // Method net/minecraft/world/item/equipment/ArmorMaterial.repairIngredient:()Lnet/minecraft/tags/TagKey;
        61: invokevirtual #235                // Method repairable:(Lnet/minecraft/tags/TagKey;)Lnet/minecraft/world/item/Item$Properties;
        64: areturn

  public net.minecraft.world.item.Item$Properties wolfArmor(net.minecraft.world.item.equipment.ArmorMaterial);
    Code:
         0: aload_0
         1: getstatic     #478                // Field net/minecraft/world/item/equipment/ArmorType.BODY:Lnet/minecraft/world/item/equipment/ArmorType;
         4: aload_1
         5: invokevirtual #441                // Method net/minecraft/world/item/equipment/ArmorMaterial.durability:()I
         8: invokevirtual #444                // Method net/minecraft/world/item/equipment/ArmorType.getDurability:(I)I
        11: invokevirtual #228                // Method durability:(I)Lnet/minecraft/world/item/Item$Properties;
        14: aload_1
        15: getstatic     #478                // Field net/minecraft/world/item/equipment/ArmorType.BODY:Lnet/minecraft/world/item/equipment/ArmorType;
        18: invokevirtual #450                // Method net/minecraft/world/item/equipment/ArmorMaterial.createAttributes:(Lnet/minecraft/world/item/equipment/ArmorType;)Lnet/minecraft/world/item/component/ItemAttributeModifiers;
        21: invokevirtual #406                // Method attributes:(Lnet/minecraft/world/item/component/ItemAttributeModifiers;)Lnet/minecraft/world/item/Item$Properties;
        24: aload_1
        25: invokevirtual #475                // Method net/minecraft/world/item/equipment/ArmorMaterial.repairIngredient:()Lnet/minecraft/tags/TagKey;
        28: invokevirtual #235                // Method repairable:(Lnet/minecraft/tags/TagKey;)Lnet/minecraft/world/item/Item$Properties;
        31: getstatic     #173                // Field net/minecraft/core/component/DataComponents.EQUIPPABLE:Lnet/minecraft/core/component/DataComponentType;
        34: getstatic     #482                // Field net/minecraft/world/entity/EquipmentSlot.BODY:Lnet/minecraft/world/entity/EquipmentSlot;
        37: invokestatic  #176                // Method net/minecraft/world/item/equipment/Equippable.builder:(Lnet/minecraft/world/entity/EquipmentSlot;)Lnet/minecraft/world/item/equipment/Equippable$Builder;
        40: aload_1
        41: invokevirtual #459                // Method net/minecraft/world/item/equipment/ArmorMaterial.equipSound:()Lnet/minecraft/core/Holder;
        44: invokevirtual #463                // Method net/minecraft/world/item/equipment/Equippable$Builder.setEquipSound:(Lnet/minecraft/core/Holder;)Lnet/minecraft/world/item/equipment/Equippable$Builder;
        47: aload_1
        48: invokevirtual #467                // Method net/minecraft/world/item/equipment/ArmorMaterial.assetId:()Lnet/minecraft/resources/ResourceKey;
        51: invokevirtual #471                // Method net/minecraft/world/item/equipment/Equippable$Builder.setAsset:(Lnet/minecraft/resources/ResourceKey;)Lnet/minecraft/world/item/equipment/Equippable$Builder;
        54: iconst_1
        55: anewarray     #140                // class net/minecraft/core/Holder
        58: dup
        59: iconst_0
        60: getstatic     #487                // Field net/minecraft/world/entity/EntityType.WOLF:Lnet/minecraft/world/entity/EntityType;
        63: invokevirtual #491                // Method net/minecraft/world/entity/EntityType.builtInRegistryHolder:()Lnet/minecraft/core/Holder$Reference;
        66: aastore
        67: invokestatic  #148                // InterfaceMethod net/minecraft/core/HolderSet.direct:([Lnet/minecraft/core/Holder;)Lnet/minecraft/core/HolderSet$Direct;
        70: invokevirtual #492                // Method net/minecraft/world/item/equipment/Equippable$Builder.setAllowedEntities:(Lnet/minecraft/core/HolderSet;)Lnet/minecraft/world/item/equipment/Equippable$Builder;
        73: iconst_1
        74: invokevirtual #496                // Method net/minecraft/world/item/equipment/Equippable$Builder.setCanBeSheared:(Z)Lnet/minecraft/world/item/equipment/Equippable$Builder;
        77: getstatic     #499                // Field net/minecraft/core/registries/BuiltInRegistries.SOUND_EVENT:Lnet/minecraft/core/Registry;
        80: getstatic     #503                // Field net/minecraft/sounds/SoundEvents.ARMOR_UNEQUIP_WOLF:Lnet/minecraft/sounds/SoundEvent;
        83: invokeinterface #507,  2          // InterfaceMethod net/minecraft/core/Registry.wrapAsHolder:(Ljava/lang/Object;)Lnet/minecraft/core/Holder;
        88: invokevirtual #513                // Method net/minecraft/world/item/equipment/Equippable$Builder.setShearingSound:(Lnet/minecraft/core/Holder;)Lnet/minecraft/world/item/equipment/Equippable$Builder;
        91: invokevirtual #182                // Method net/minecraft/world/item/equipment/Equippable$Builder.build:()Lnet/minecraft/world/item/equipment/Equippable;
        94: invokevirtual #56                 // Method component:(Lnet/minecraft/core/component/DataComponentType;Ljava/lang/Object;)Lnet/minecraft/world/item/Item$Properties;
        97: getstatic     #516                // Field net/minecraft/core/component/DataComponents.BREAK_SOUND:Lnet/minecraft/core/component/DataComponentType;
       100: getstatic     #519                // Field net/minecraft/sounds/SoundEvents.WOLF_ARMOR_BREAK:Lnet/minecraft/core/Holder$Reference;
       103: invokevirtual #56                 // Method component:(Lnet/minecraft/core/component/DataComponentType;Ljava/lang/Object;)Lnet/minecraft/world/item/Item$Properties;
       106: iconst_1
       107: invokevirtual #523                // Method stacksTo:(I)Lnet/minecraft/world/item/Item$Properties;
       110: areturn

  public net.minecraft.world.item.Item$Properties horseArmor(net.minecraft.world.item.equipment.ArmorMaterial);
    Code:
         0: getstatic     #526                // Field net/minecraft/core/registries/BuiltInRegistries.ENTITY_TYPE:Lnet/minecraft/core/DefaultedRegistry;
         3: invokestatic  #163                // Method net/minecraft/core/registries/BuiltInRegistries.acquireBootstrapRegistrationLookup:(Lnet/minecraft/core/Registry;)Lnet/minecraft/core/HolderGetter;
         6: astore_2
         7: aload_0
         8: aload_1
         9: getstatic     #478                // Field net/minecraft/world/item/equipment/ArmorType.BODY:Lnet/minecraft/world/item/equipment/ArmorType;
        12: invokevirtual #450                // Method net/minecraft/world/item/equipment/ArmorMaterial.createAttributes:(Lnet/minecraft/world/item/equipment/ArmorType;)Lnet/minecraft/world/item/component/ItemAttributeModifiers;
        15: invokevirtual #406                // Method attributes:(Lnet/minecraft/world/item/component/ItemAttributeModifiers;)Lnet/minecraft/world/item/Item$Properties;
        18: getstatic     #173                // Field net/minecraft/core/component/DataComponents.EQUIPPABLE:Lnet/minecraft/core/component/DataComponentType;
        21: getstatic     #482                // Field net/minecraft/world/entity/EquipmentSlot.BODY:Lnet/minecraft/world/entity/EquipmentSlot;
        24: invokestatic  #176                // Method net/minecraft/world/item/equipment/Equippable.builder:(Lnet/minecraft/world/entity/EquipmentSlot;)Lnet/minecraft/world/item/equipment/Equippable$Builder;
        27: getstatic     #529                // Field net/minecraft/sounds/SoundEvents.HORSE_ARMOR:Lnet/minecraft/core/Holder$Reference;
        30: invokevirtual #463                // Method net/minecraft/world/item/equipment/Equippable$Builder.setEquipSound:(Lnet/minecraft/core/Holder;)Lnet/minecraft/world/item/equipment/Equippable$Builder;
        33: aload_1
        34: invokevirtual #467                // Method net/minecraft/world/item/equipment/ArmorMaterial.assetId:()Lnet/minecraft/resources/ResourceKey;
        37: invokevirtual #471                // Method net/minecraft/world/item/equipment/Equippable$Builder.setAsset:(Lnet/minecraft/resources/ResourceKey;)Lnet/minecraft/world/item/equipment/Equippable$Builder;
        40: aload_2
        41: getstatic     #532                // Field net/minecraft/tags/EntityTypeTags.CAN_WEAR_HORSE_ARMOR:Lnet/minecraft/tags/TagKey;
        44: invokeinterface #167,  2          // InterfaceMethod net/minecraft/core/HolderGetter.getOrThrow:(Lnet/minecraft/tags/TagKey;)Lnet/minecraft/core/HolderSet$Named;
        49: invokevirtual #492                // Method net/minecraft/world/item/equipment/Equippable$Builder.setAllowedEntities:(Lnet/minecraft/core/HolderSet;)Lnet/minecraft/world/item/equipment/Equippable$Builder;
        52: iconst_0
        53: invokevirtual #537                // Method net/minecraft/world/item/equipment/Equippable$Builder.setDamageOnHurt:(Z)Lnet/minecraft/world/item/equipment/Equippable$Builder;
        56: iconst_1
        57: invokevirtual #496                // Method net/minecraft/world/item/equipment/Equippable$Builder.setCanBeSheared:(Z)Lnet/minecraft/world/item/equipment/Equippable$Builder;
        60: getstatic     #540                // Field net/minecraft/sounds/SoundEvents.HORSE_ARMOR_UNEQUIP:Lnet/minecraft/core/Holder$Reference;
        63: invokevirtual #513                // Method net/minecraft/world/item/equipment/Equippable$Builder.setShearingSound:(Lnet/minecraft/core/Holder;)Lnet/minecraft/world/item/equipment/Equippable$Builder;
        66: invokevirtual #182                // Method net/minecraft/world/item/equipment/Equippable$Builder.build:()Lnet/minecraft/world/item/equipment/Equippable;
        69: invokevirtual #56                 // Method component:(Lnet/minecraft/core/component/DataComponentType;Ljava/lang/Object;)Lnet/minecraft/world/item/Item$Properties;
        72: iconst_1
        73: invokevirtual #523                // Method stacksTo:(I)Lnet/minecraft/world/item/Item$Properties;
        76: areturn

  public net.minecraft.world.item.Item$Properties nautilusArmor(net.minecraft.world.item.equipment.ArmorMaterial);
    Code:
         0: getstatic     #526                // Field net/minecraft/core/registries/BuiltInRegistries.ENTITY_TYPE:Lnet/minecraft/core/DefaultedRegistry;
         3: invokestatic  #163                // Method net/minecraft/core/registries/BuiltInRegistries.acquireBootstrapRegistrationLookup:(Lnet/minecraft/core/Registry;)Lnet/minecraft/core/HolderGetter;
         6: astore_2
         7: aload_0
         8: aload_1
         9: getstatic     #478                // Field net/minecraft/world/item/equipment/ArmorType.BODY:Lnet/minecraft/world/item/equipment/ArmorType;
        12: invokevirtual #450                // Method net/minecraft/world/item/equipment/ArmorMaterial.createAttributes:(Lnet/minecraft/world/item/equipment/ArmorType;)Lnet/minecraft/world/item/component/ItemAttributeModifiers;
        15: invokevirtual #406                // Method attributes:(Lnet/minecraft/world/item/component/ItemAttributeModifiers;)Lnet/minecraft/world/item/Item$Properties;
        18: getstatic     #173                // Field net/minecraft/core/component/DataComponents.EQUIPPABLE:Lnet/minecraft/core/component/DataComponentType;
        21: getstatic     #482                // Field net/minecraft/world/entity/EquipmentSlot.BODY:Lnet/minecraft/world/entity/EquipmentSlot;
        24: invokestatic  #176                // Method net/minecraft/world/item/equipment/Equippable.builder:(Lnet/minecraft/world/entity/EquipmentSlot;)Lnet/minecraft/world/item/equipment/Equippable$Builder;
        27: getstatic     #543                // Field net/minecraft/sounds/SoundEvents.ARMOR_EQUIP_NAUTILUS:Lnet/minecraft/core/Holder$Reference;
        30: invokevirtual #463                // Method net/minecraft/world/item/equipment/Equippable$Builder.setEquipSound:(Lnet/minecraft/core/Holder;)Lnet/minecraft/world/item/equipment/Equippable$Builder;
        33: aload_1
        34: invokevirtual #467                // Method net/minecraft/world/item/equipment/ArmorMaterial.assetId:()Lnet/minecraft/resources/ResourceKey;
        37: invokevirtual #471                // Method net/minecraft/world/item/equipment/Equippable$Builder.setAsset:(Lnet/minecraft/resources/ResourceKey;)Lnet/minecraft/world/item/equipment/Equippable$Builder;
        40: aload_2
        41: getstatic     #546                // Field net/minecraft/tags/EntityTypeTags.CAN_WEAR_NAUTILUS_ARMOR:Lnet/minecraft/tags/TagKey;
        44: invokeinterface #167,  2          // InterfaceMethod net/minecraft/core/HolderGetter.getOrThrow:(Lnet/minecraft/tags/TagKey;)Lnet/minecraft/core/HolderSet$Named;
        49: invokevirtual #492                // Method net/minecraft/world/item/equipment/Equippable$Builder.setAllowedEntities:(Lnet/minecraft/core/HolderSet;)Lnet/minecraft/world/item/equipment/Equippable$Builder;
        52: iconst_0
        53: invokevirtual #537                // Method net/minecraft/world/item/equipment/Equippable$Builder.setDamageOnHurt:(Z)Lnet/minecraft/world/item/equipment/Equippable$Builder;
        56: iconst_1
        57: invokevirtual #549                // Method net/minecraft/world/item/equipment/Equippable$Builder.setEquipOnInteract:(Z)Lnet/minecraft/world/item/equipment/Equippable$Builder;
        60: iconst_1
        61: invokevirtual #496                // Method net/minecraft/world/item/equipment/Equippable$Builder.setCanBeSheared:(Z)Lnet/minecraft/world/item/equipment/Equippable$Builder;
        64: getstatic     #552                // Field net/minecraft/sounds/SoundEvents.ARMOR_UNEQUIP_NAUTILUS:Lnet/minecraft/core/Holder$Reference;
        67: invokevirtual #513                // Method net/minecraft/world/item/equipment/Equippable$Builder.setShearingSound:(Lnet/minecraft/core/Holder;)Lnet/minecraft/world/item/equipment/Equippable$Builder;
        70: invokevirtual #182                // Method net/minecraft/world/item/equipment/Equippable$Builder.build:()Lnet/minecraft/world/item/equipment/Equippable;
        73: invokevirtual #56                 // Method component:(Lnet/minecraft/core/component/DataComponentType;Ljava/lang/Object;)Lnet/minecraft/world/item/Item$Properties;
        76: iconst_1
        77: invokevirtual #523                // Method stacksTo:(I)Lnet/minecraft/world/item/Item$Properties;
        80: areturn

  public net.minecraft.world.item.Item$Properties trimMaterial(net.minecraft.resources.ResourceKey<net.minecraft.world.item.equipment.trim.TrimMaterial>);
    Code:
         0: aload_0
         1: getstatic     #555                // Field net/minecraft/core/component/DataComponents.PROVIDES_TRIM_MATERIAL:Lnet/minecraft/core/component/DataComponentType;
         4: aload_1
         5: invokevirtual #254                // Method delayedHolderComponent:(Lnet/minecraft/core/component/DataComponentType;Lnet/minecraft/resources/ResourceKey;)Lnet/minecraft/world/item/Item$Properties;
         8: areturn

  public net.minecraft.world.item.Item$Properties requiredFeatures(net.minecraft.world.flag.FeatureFlag...);
    Code:
         0: aload_0
         1: getstatic     #558                // Field net/minecraft/world/flag/FeatureFlags.REGISTRY:Lnet/minecraft/world/flag/FeatureFlagRegistry;
         4: aload_1
         5: invokevirtual #562                // Method net/minecraft/world/flag/FeatureFlagRegistry.subset:([Lnet/minecraft/world/flag/FeatureFlag;)Lnet/minecraft/world/flag/FeatureFlagSet;
         8: putfield      #23                 // Field requiredFeatures:Lnet/minecraft/world/flag/FeatureFlagSet;
        11: aload_0
        12: areturn

  public net.minecraft.world.item.Item$Properties requiredFeatures(net.minecraft.world.flag.FeatureFlagSet);
    Code:
         0: getstatic     #558                // Field net/minecraft/world/flag/FeatureFlags.REGISTRY:Lnet/minecraft/world/flag/FeatureFlagRegistry;
         3: aload_1
         4: invokevirtual #568                // Method net/minecraft/world/flag/FeatureFlagRegistry.isSubset:(Lnet/minecraft/world/flag/FeatureFlagSet;)Z
         7: ifne          21
        10: new           #572                // class java/lang/IllegalArgumentException
        13: dup
        14: ldc_w         #574                // String Mismatched flag sets
        17: invokespecial #576                // Method java/lang/IllegalArgumentException."<init>":(Ljava/lang/String;)V
        20: athrow
        21: aload_0
        22: aload_1
        23: putfield      #23                 // Field requiredFeatures:Lnet/minecraft/world/flag/FeatureFlagSet;
        26: aload_0
        27: areturn

  public net.minecraft.world.item.Item$Properties setId(net.minecraft.resources.ResourceKey<net.minecraft.world.item.Item>);
    Code:
         0: aload_0
         1: aload_1
         2: putfield      #579                // Field id:Lnet/minecraft/resources/ResourceKey;
         5: aload_0
         6: areturn

  public net.minecraft.world.item.Item$Properties overrideDescription(java.lang.String);
    Code:
         0: aload_0
         1: aload_1
         2: invokestatic  #582                // InterfaceMethod net/minecraft/resources/DependantName.fixed:(Ljava/lang/Object;)Lnet/minecraft/resources/DependantName;
         5: putfield      #30                 // Field descriptionId:Lnet/minecraft/resources/DependantName;
         8: aload_0
         9: areturn

  public net.minecraft.world.item.Item$Properties useBlockDescriptionPrefix();
    Code:
         0: aload_0
         1: getstatic     #588                // Field BLOCK_DESCRIPTION_ID:Lnet/minecraft/resources/DependantName;
         4: putfield      #30                 // Field descriptionId:Lnet/minecraft/resources/DependantName;
         7: aload_0
         8: areturn

  public net.minecraft.world.item.Item$Properties useItemDescriptionPrefix();
    Code:
         0: aload_0
         1: getstatic     #26                 // Field ITEM_DESCRIPTION_ID:Lnet/minecraft/resources/DependantName;
         4: putfield      #30                 // Field descriptionId:Lnet/minecraft/resources/DependantName;
         7: aload_0
         8: areturn

  protected java.lang.String effectiveDescriptionId();
    Code:
         0: aload_0
         1: getfield      #30                 // Field descriptionId:Lnet/minecraft/resources/DependantName;
         4: aload_0
         5: invokevirtual #601                // Method itemIdOrThrow:()Lnet/minecraft/resources/ResourceKey;
         8: invokeinterface #604,  2          // InterfaceMethod net/minecraft/resources/DependantName.get:(Lnet/minecraft/resources/ResourceKey;)Ljava/lang/Object;
        13: checkcast     #607                // class java/lang/String
        16: areturn

  public net.minecraft.resources.Identifier effectiveModel();
    Code:
         0: aload_0
         1: getfield      #37                 // Field model:Lnet/minecraft/resources/DependantName;
         4: aload_0
         5: invokevirtual #601                // Method itemIdOrThrow:()Lnet/minecraft/resources/ResourceKey;
         8: invokeinterface #604,  2          // InterfaceMethod net/minecraft/resources/DependantName.get:(Lnet/minecraft/resources/ResourceKey;)Ljava/lang/Object;
        13: checkcast     #609                // class net/minecraft/resources/Identifier
        16: areturn

  public <T> net.minecraft.world.item.Item$Properties component(net.minecraft.core.component.DataComponentType<T>, T);
    Code:
         0: aload_0
         1: aload_0
         2: getfield      #11                 // Field componentInitializer:Lnet/minecraft/core/component/DataComponentInitializers$Initializer;
         5: aload_1
         6: aload_2
         7: invokeinterface #611,  3          // InterfaceMethod net/minecraft/core/component/DataComponentInitializers$Initializer.add:(Lnet/minecraft/core/component/DataComponentType;Ljava/lang/Object;)Lnet/minecraft/core/component/DataComponentInitializers$Initializer;
        12: putfield      #11                 // Field componentInitializer:Lnet/minecraft/core/component/DataComponentInitializers$Initializer;
        15: aload_0
        16: areturn

  public <T> net.minecraft.world.item.Item$Properties delayedComponent(net.minecraft.core.component.DataComponentType<T>, net.minecraft.core.component.DataComponentInitializers$SingleComponentInitializer<T>);
    Code:
         0: aload_0
         1: aload_0
         2: getfield      #11                 // Field componentInitializer:Lnet/minecraft/core/component/DataComponentInitializers$Initializer;
         5: aload_2
         6: aload_1
         7: invokeinterface #616,  2          // InterfaceMethod net/minecraft/core/component/DataComponentInitializers$SingleComponentInitializer.asInitializer:(Lnet/minecraft/core/component/DataComponentType;)Lnet/minecraft/core/component/DataComponentInitializers$Initializer;
        12: invokeinterface #622,  2          // InterfaceMethod net/minecraft/core/component/DataComponentInitializers$Initializer.andThen:(Lnet/minecraft/core/component/DataComponentInitializers$Initializer;)Lnet/minecraft/core/component/DataComponentInitializers$Initializer;
        17: putfield      #11                 // Field componentInitializer:Lnet/minecraft/core/component/DataComponentInitializers$Initializer;
        20: aload_0
        21: areturn

  public <T> net.minecraft.world.item.Item$Properties delayedHolderComponent(net.minecraft.core.component.DataComponentType<net.minecraft.core.Holder<T>>, net.minecraft.resources.ResourceKey<T>);
    Code:
         0: aload_0
         1: aload_0
         2: getfield      #11                 // Field componentInitializer:Lnet/minecraft/core/component/DataComponentInitializers$Initializer;
         5: aload_1
         6: aload_2
         7: invokedynamic #626,  0            // InvokeDynamic #4:run:(Lnet/minecraft/core/component/DataComponentType;Lnet/minecraft/resources/ResourceKey;)Lnet/minecraft/core/component/DataComponentInitializers$Initializer;
        12: invokeinterface #622,  2          // InterfaceMethod net/minecraft/core/component/DataComponentInitializers$Initializer.andThen:(Lnet/minecraft/core/component/DataComponentInitializers$Initializer;)Lnet/minecraft/core/component/DataComponentInitializers$Initializer;
        17: putfield      #11                 // Field componentInitializer:Lnet/minecraft/core/component/DataComponentInitializers$Initializer;
        20: aload_0
        21: areturn

  public net.minecraft.world.item.Item$Properties attributes(net.minecraft.world.item.component.ItemAttributeModifiers);
    Code:
         0: aload_0
         1: getstatic     #629                // Field net/minecraft/core/component/DataComponents.ATTRIBUTE_MODIFIERS:Lnet/minecraft/core/component/DataComponentType;
         4: aload_1
         5: invokevirtual #56                 // Method component:(Lnet/minecraft/core/component/DataComponentType;Ljava/lang/Object;)Lnet/minecraft/world/item/Item$Properties;
         8: areturn

  static {};
    Code:
         0: invokedynamic #714,  0            // InvokeDynamic #7:get:()Lnet/minecraft/resources/DependantName;
         5: putstatic     #588                // Field BLOCK_DESCRIPTION_ID:Lnet/minecraft/resources/DependantName;
         8: invokedynamic #715,  0            // InvokeDynamic #8:get:()Lnet/minecraft/resources/DependantName;
        13: putstatic     #26                 // Field ITEM_DESCRIPTION_ID:Lnet/minecraft/resources/DependantName;
        16: return
}
